csecraft/__init__.py
csecraft/main.py
csecraft/schemas/__init__.py
csecraft/schemas/main.py
csecraft-0.1.2.dist-info/LICENSE
csecraft-0.1.2.dist-info/METADATA
csecraft-0.1.2.dist-info/WHEEL
csecraft-0.1.2.dist-info/top_level.txt
csecraft-0.1.2.dist-info/RECORD
