Metadata-Version: 2.1
Name: csecraft
Version: 0.1.2
Summary: A Python library for easily interacting with the Google Custom Search API
Home-page: https://github.com/benkimz/csecraft
Author: Benard K. Wachira (@benkimz)
Maintainer: @benkimz
License: MIT
Keywords: google,cse,api,search,custom search
Platform: any
Classifier: Programming Language :: Python :: 3
Classifier: License :: OSI Approved :: MIT License
Classifier: Operating System :: OS Independent
License-File: LICENSE
Requires-Dist: requests
Requires-Dist: pydantic
Requires-Dist: typing
